MANIFEST.in
RELEASE-VERSION
pavement.py
paver-minilib.zip
setup.py
version.py
arduino_helpers/__init__.py
arduino_helpers/__init__.pyc
arduino_helpers/context.py
arduino_helpers/context.pyc
arduino_helpers/upload.py
arduino_helpers/upload.pyc
arduino_helpers.egg-info/PKG-INFO
arduino_helpers.egg-info/SOURCES.txt
arduino_helpers.egg-info/dependency_links.txt
arduino_helpers.egg-info/pbr.json
arduino_helpers.egg-info/requires.txt
arduino_helpers.egg-info/top_level.txt
arduino_helpers/bin/__init__.py
arduino_helpers/bin/__init__.pyc
arduino_helpers/bin/upload.py
arduino_helpers/driver/arduino.cat
arduino_helpers/driver/arduino.inf
arduino_helpers/hardware/__init__.py
arduino_helpers/hardware/__init__.pyc
arduino_helpers/hardware/arduino.py
arduino_helpers/hardware/arduino.pyc
arduino_helpers/hardware/boards.py
arduino_helpers/hardware/boards.pyc
arduino_helpers/hardware/platform.py
arduino_helpers/hardware/platform.pyc
arduino_helpers/hardware/tools.py
arduino_helpers/hardware/tools.pyc
arduino_helpers/hardware/teensy/__init__.py
arduino_helpers/hardware/teensy/__init__.pyc
arduino_helpers/hardware/teensy/adc.py
arduino_helpers/hardware/teensy/adc.pyc
arduino_helpers/hardware/teensy/dma.py
arduino_helpers/hardware/teensy/dma.pyc
arduino_helpers/hardware/teensy/pdb.py
arduino_helpers/hardware/teensy/pdb.pyc
arduino_helpers/hardware/teensy/pit.py
arduino_helpers/hardware/teensy/pit.pyc
arduino_helpers/hardware/teensy/sim.py
arduino_helpers/lib/arduino-1.0.5-base/revisions.txt
arduino_helpers/lib/arduino-1.0.5-base/hardware/arduino/boards.txt
arduino_helpers/lib/arduino-1.0.5-base/hardware/arduino/programmers.txt
arduino_helpers/lib/arduino-1.0.5-base/hardware/arduino/bootloaders/atmega/ATmegaBOOT_168.c
arduino_helpers/lib/arduino-1.0.5-base/hardware/arduino/bootloaders/atmega/ATmegaBOOT_168_atmega1280.hex
arduino_helpers/lib/arduino-1.0.5-base/hardware/arduino/bootloaders/atmega/ATmegaBOOT_168_atmega328.hex
arduino_helpers/lib/arduino-1.0.5-base/hardware/arduino/bootloaders/atmega/ATmegaBOOT_168_atmega328_pro_8MHz.hex
arduino_helpers/lib/arduino-1.0.5-base/hardware/arduino/bootloaders/atmega/ATmegaBOOT_168_diecimila.hex
