Metadata-Version: 1.0
Name: arduino-helpers
Version: 0.3.post18
Summary: Helper functions for reading configs, etc. from an installed Arduino directory.
Home-page: http://github.com/wheeler-microfluidics/arduino-helpers.git
Author: Christian Fobel
Author-email: christian@fobel.net
License: GPLv2
Platform: UNKNOWN
